{
  "project_info": {
    "project_number": "211423972416",
    "project_id": "medico-pro",
    "storage_bucket": "medico-pro.appspot.com"
  },
  "client": [
    {
      "client_info": {
        "mobilesdk_app_id": "1:211423972416:android:18e511f01fa6f84159a3a5",
        "android_client_info": {
          "package_name": "com.example.medico"
        }
      },
      "oauth_client": [],
      "api_key": [
        {
          "current_key": "AIzaSyA-BcS-6LSRYpF1h6fwpbqCA6jYu87A8mM"
        }
      ],
      "services": {
        "appinvite_service": {
          "other_platform_oauth_client": []
        }
      }
    }
  ],
  "configuration_version": "1"
}